q2numfmt/__init__.py
q2numfmt/core.py
q2numfmt/version.py
q2numfmt-0.1.1.dist-info/LICENSE
q2numfmt-0.1.1.dist-info/METADATA
q2numfmt-0.1.1.dist-info/WHEEL
q2numfmt-0.1.1.dist-info/RECORD
