Metadata-Version: 2.1
Name: q2numfmt
Version: 0.1.1
Summary: Excel-style number formatting for Python.
Author: Andrei Puchko
Author-email: andrei.puchko@gmx.de
Requires-Python: >=3.11,<4.0
Classifier: Programming Language :: Python :: 3
Classifier: Programming Language :: Python :: 3.11
